json2bson.py
json2bson-0.0.3.dist-info/LICENSE
json2bson-0.0.3.dist-info/METADATA
json2bson-0.0.3.dist-info/WHEEL
json2bson-0.0.3.dist-info/entry_points.txt
json2bson-0.0.3.dist-info/top_level.txt
json2bson-0.0.3.dist-info/RECORD
