Metadata-Version: 2.1
Name: json2bson
Version: 0.0.3
Summary: CLI tool to convert JSON files to BSON.
Home-page: https://github.com/luiscruz/json2bson
Author: Luis Cruz
Author-email: luismirandacruz@gmail.com
License: UNKNOWN
Platform: UNKNOWN
Classifier: Programming Language :: Python :: 3
Classifier: License :: OSI Approved :: Apache Software License
Classifier: Operating System :: OS Independent
Requires-Dist: Click
Requires-Dist: bson
